{
  "$schema": "https://developer.microsoft.com/json-schemas/fabric/item/report/definition/visualContainer/2.7.0/schema.json",
  "name": "a66c2c6eaadcae8cd270",
  "position": {
    "x": 799.1275574404624,
    "y": 27.984738929481129,
    "z": 4000,
    "height": 125.93132518266506,
    "width": 106.82077332960495,
    "tabOrder": 1000
  },
  "visual": {
    "visualType": "image",
    "objects": {
      "image": [
        {
          "properties": {
            "sourceFile": {
              "image": {
                "name": {
                  "expr": {
                    "Literal": {
                      "Value": "'Unknown.png'"
                    }
                  }
                },
                "url": {
                  "expr": {
                    "ResourcePackageItem": {
                      "PackageName": "RegisteredResources",
                      "PackageType": 1,
                      "ItemName": "Unknown5811137082259169.png"
                    }
                  }
                },
                "scaling": {
                  "expr": {
                    "Literal": {
                      "Value": "'Normal'"
                    }
                  }
                }
              }
            }
          }
        }
      ]
    },
    "drillFilterOtherVisuals": true
  },
  "parentGroupName": "649b28dd0e4ba44ac723"
}